py_orchestrate/__init__.py
py_orchestrate/decorators.py
py_orchestrate/example.py
py_orchestrate/models.py
py_orchestrate/orchestrator.py
py_orchestrate-1.0.1.dist-info/METADATA
py_orchestrate-1.0.1.dist-info/WHEEL
py_orchestrate-1.0.1.dist-info/licenses/LICENSE
py_orchestrate-1.0.1.dist-info/RECORD
