Metadata-Version: 2.4
Name: py-orchestrate
Version: 1.0.1
Summary: A Python workflow orchestrator with embedded SQLite database, similar to Durable Functions
Project-URL: Homepage, https://github.com/mymac/py-orchestrate
Project-URL: Documentation, https://github.com/mymac/py-orchestrate#readme
Project-URL: Repository, https://github.com/mymac/py-orchestrate.git
Project-URL: Issues, https://github.com/mymac/py-orchestrate/issues
Project-URL: Changelog, https://github.com/mymac/py-orchestrate/releases
Author: py-orchestrate contributors
Maintainer: py-orchestrate contributors
License: MIT
License-File: LICENSE
Keywords: durable-functions,fault-tolerance,orchestrator,persistence,sqlite,task-orchestration,workflow,workflow-engine
Classifier: Development Status :: 4 - Beta
Classifier: Intended Audience :: Developers
Classifier: License :: OSI Approved :: MIT License
Classifier: Operating System :: OS Independent
Classifier: Programming Language :: Python :: 3
Classifier: Programming Language :: Python :: 3.12
Classifier: Programming Language :: Python :: 3.13
Classifier: Topic :: Database
Classifier: Topic :: Software Development :: Libraries :: Python Modules
Classifier: Topic :: System :: Distributed Computing
Requires-Python: >=3.12
Provides-Extra: dev
Requires-Dist: black>=22.0.0; extra == 'dev'
Requires-Dist: build>=0.10.0; extra == 'dev'
Requires-Dist: mypy>=1.0.0; extra == 'dev'
Requires-Dist: pytest>=7.0.0; extra == 'dev'
Requires-Dist: twine>=4.0.0; extra == 'dev'
